{
	"instance" : {
		"aYes" : "PaulDeBruicker 3/31/2010 11:00",
		"showTestResults" : "PaulDeBruicker 3/31/2010 17:21",
		"bYes:" : "PaulDeBruicker 3/31/2010 11:00",
		"enoughResults" : "PaulDeBruicker 3/31/2010 12:59",
		"testDuration" : "PaulDeBruicker 3/31/2010 15:30",
		"aConverts:" : "PaulDeBruicker 3/31/2010 12:42",
		"aConversion" : "PaulDeBruicker 3/31/2010 12:35",
		"confidenceLevel" : "PaulDeBruicker 3/31/2010 11:04",
		"initialize" : "PaulDeBruicker 3/31/2010 16:55",
		"bConverts" : "PaulDeBruicker 3/31/2010 12:42",
		"bYes" : "PaulDeBruicker 3/31/2010 11:00",
		"testName:" : "PaulDeBruicker 3/31/2010 10:25",
		"aYes:" : "PaulDeBruicker 3/31/2010 11:00",
		"bViews:" : "PaulDeBruicker 3/31/2010 11:00",
		"endDate" : "PaulDeBruicker 3/31/2010 10:25",
		"bConverts:" : "PaulDeBruicker 3/31/2010 12:42",
		"startDate:" : "PaulDeBruicker 3/31/2010 10:25",
		"views" : "PaulDeBruicker 3/31/2010 11:00",
		"bViews" : "PaulDeBruicker 3/31/2010 11:00",
		"goal" : "PaulDeBruicker 3/31/2010 10:25",
		"aConverts" : "PaulDeBruicker 3/31/2010 12:42",
		"testName" : "PaulDeBruicker 3/31/2010 10:25",
		"getAorB" : "PaulDeBruicker 3/31/2010 11:31",
		"b:" : "PaulDeBruicker 3/31/2010 10:25",
		"winner:" : "PaulDeBruicker 3/31/2010 11:23",
		"enoughResults:" : "PaulDeBruicker 3/31/2010 12:59",
		"bConversion" : "PaulDeBruicker 3/31/2010 12:35",
		"goal:" : "PaulDeBruicker 3/31/2010 10:25",
		"testResults" : "PaulDeBruicker 3/31/2010 15:15",
		"highConfidence" : "PaulDeBruicker 3/31/2010 12:59",
		"endDate:" : "PaulDeBruicker 3/31/2010 10:25",
		"aViews:" : "PaulDeBruicker 3/31/2010 11:00",
		"description:" : "PaulDeBruicker 3/31/2010 10:25",
		"highConfidence:" : "PaulDeBruicker 3/31/2010 12:59",
		"description" : "PaulDeBruicker 3/31/2010 10:25",
		"a" : "PaulDeBruicker 3/31/2010 10:25",
		"winner" : "PaulDeBruicker 3/31/2010 10:25",
		"b" : "PaulDeBruicker 3/31/2010 10:25",
		"startDate" : "PaulDeBruicker 3/31/2010 10:25",
		"aViews" : "PaulDeBruicker 3/31/2010 11:00",
		"a:" : "PaulDeBruicker 3/31/2010 10:25"
	},
	"class" : {
		"DesiredConfidenceLevel" : "PaulDeBruicker 3/31/2010 13:59",
		"DesiredConfidenceLevel:" : "PaulDeBruicker 3/31/2010 13:59",
		"users" : "PaulDeBruicker 3/31/2010 17:46",
		"recordConversion:by:" : "PaulDeBruicker 3/31/2010 17:55",
		"newTest:a:b:" : "PaulDeBruicker 3/31/2010 10:55",
		"users:" : "PaulDeBruicker 3/31/2010 17:46",
		"showVariation:a:b:user:" : "PaulDeBruicker 3/31/2010 17:55",
		"tests:" : "PaulDeBruicker 3/31/2010 10:25",
		"tests" : "PaulDeBruicker 3/31/2010 16:50"
	}
}